{
  "articles": [
    {
      "id": "The-Infinitys-777-follower-on-Scratch",
      "title": "Scratch\u3067777\u30d5\u30a9\u30ed\u30ef\u30fc!!!!!!",
      "date": "2024/06/27",
      "thumbnail": "thumbnail.jpeg"
    },
    {
      "id": "crazy-Tokyo-gubernatorial-election-2024",
      "title": "\u30e4\u30d0\u904e\u304e\u308b\u4eca\u5e74\u306e\u6771\u4eac\u90fd\u77e5\u4e8b\u9078\u6319",
      "date": "2024/06/21",
      "thumbnail": "thumbnail.jpg"
    },
    {
      "id": "The_Infinitys-666-follower-on-Scratch",
      "title": "Scratch\u306e\u30d5\u30a9\u30ed\u30ef\u30fc\u304c666\u4eba\u306b\u306a\u308a\u307e\u3057\u305f\u3002",
      "date": "2024/06/1n",
      "thumbnail": "thumbnail.svg"
    },
    {
      "id": "The_Infinitys-700-follower-on-Scratch",
      "title": "Scratch\u3067\u30d5\u30a9\u30ed\u30ef\u30fc700\u4eba\u3068\u3063\u305f\u3069\u30fc\uff01",
      "date": "2024/06/19",
      "thumbnail": "thumbnail.jpeg"
    },
    {
      "id": "make-search-function",
      "title": "\u691c\u7d22\u6a5f\u80fd\u3092\u642d\u8f09\u3059\u308b",
      "date": "2024/06/19",
      "thumbnail": "thumbnail.png"
    },
    {
      "id": "news-changed-directory",
      "title": "\u304a\u77e5\u3089\u305b - \u30c7\u30a3\u30ec\u30af\u30c8\u30ea\u540d\u304c\u5909\u308f\u308a\u307e\u3057\u305f \u4ed6\u4e8c\u3064",
      "date": "2024/06/17",
      "thumbnail": "thumbnail.png"
    },
    {
      "id": "SEO_4",
      "title": "SEO\u5bfe\u7b56\u305d\u306e4",
      "date": "2024/06/16",
      "thumbnail": "thumbnail.jpeg"
    },
    {
      "id": "powerup-speed",
      "title": "\u30d6\u30ed\u30b0\u306e\u8868\u793a\u304c\u65e9\u304f\u306a\u308a\u307e\u3057\u305f\u3002",
      "date": "2024/06/16",
      "thumbnail": "thumbnail.png"
    },
    {
      "id": "update_and_add_blog_list",
      "title": "\u30d6\u30ed\u30b0\u3092\u3055\u3089\u306b\u9032\u5316\u3055\u305b\u308b",
      "date": "2024/06/15",
      "thumbnail": "thumbnail.jpeg"
    },
    {
      "id": "The-Infinitys_1st_anniversary_comming_soon",
      "title": "\u3082\u3046\u76f4\u30501\u5468\u5e74!",
      "date": "2024/06/14",
      "thumbnail": "thumbnail.png"
    },
    {
      "id": "enable-markdown",
      "title": "markdown\u3067\u30d6\u30ed\u30b0\u3092\u66f8\u3051\u308b\u3088\u3046\u306b\u3057\u305f",
      "date": "2024/06/13",
      "thumbnail": "thumbnail.png"
    },
    {
      "id": "to-understand-remix-culture",
      "title": "\u30ea\u30df\u30c3\u30af\u30b9\u6587\u5316\u3092\u7406\u89e3\u3059\u308b\u3053\u3068",
      "date": "2024/06/13",
      "thumbnail": "thumbnail.png"
    },
    {
      "id": "update-blog-to-article",
      "title": "Blog\u3092\u66f4\u65b0\u3057\u307e\u3057\u305f",
      "date": "2024/06/07",
      "thumbnail": "thumbnail.png"
    },
    {
      "id": "to-use-site-generator",
      "title": "Web\u30b5\u30a4\u30c8\u3092\u4f5c\u308b\u3068\u304d\u306b\u30b5\u30a4\u30c8\u30b8\u30a7\u30cd\u30ec\u30fc\u30bf\u3092\u4f7f\u3046\u3079\u304d\u304b\uff1f",
      "date": "2024/06/05",
      "thumbnail": "thumbnail.png"
    },
    {
      "id": "AI_technology_with_The-Infinitys",
      "title": "\u5b9f\u5199\u3058\u3083\u306a\u3044\u305e\u3001\u30ed\u30b4\u3060\u305e",
      "date": "2024/06/04",
      "thumbnail": "thumbnail.jpg"
    },
    {
      "id": "new-about-server",
      "title": "\u30b5\u30fc\u30d0\u30fc\u306b\u3064\u3044\u3066\u306e\u8a71",
      "date": "2024/06/03",
      "thumbnail": "thumbnail.png"
    },
    {
      "id": "To_all_AI_artists_who_call_themselves_AI_engineers",
      "title": "\u3053\u306e\u4fbf\u5229\u306a\u5834\u3092\u501f\u308a\u3066\u3042\u306a\u305f\u305f\u3061\u81ea\u79f0AI\u6280\u5e2b\u306b\u8a00\u308f\u305b\u3066\u9802\u304d\u307e\u3059\u3002",
      "date": "2024/06/01",
      "thumbnail": "thumbnail.png"
    },
    {
      "id": "Scratch-messages-count-tool",
      "title": "Scratch messages counter",
      "date": "2024/06/01",
      "thumbnail": "thumbnail.png"
    }
  ]
}